.gitignore
LICENSE
MANIFEST.in
MoneyMoneyPL.epj
README.md
setup.py
moneymoney_pl/__init__.py
moneymoney_pl/core.py
moneymoney_pl.egg-info/PKG-INFO
moneymoney_pl.egg-info/SOURCES.txt
moneymoney_pl.egg-info/dependency_links.txt
moneymoney_pl.egg-info/not-zip-safe
moneymoney_pl.egg-info/top_level.txt