Metadata-Version: 2.1
Name: moneymoney-pl
Version: 0.1.0
Summary: Python module to read and write LibreOffice and MS Office files using uno API
Home-page: https://github.com/turulomio/moneymoney_pl
Author: turulomio
Author-email: turulomio@yahoo.es
License: GPL-3
Classifier: Development Status :: 4 - Beta
Classifier: Intended Audience :: Developers
Classifier: Topic :: Software Development :: Build Tools
Classifier: License :: OSI Approved :: GNU General Public License v3 (GPLv3)
Classifier: Programming Language :: Python :: 3
License-File: LICENSE
